Imap2Dict_kiyoshirou/__init__.py
Imap2Dict_kiyoshirou/file_converter.py
Imap2Dict_kiyoshirou-1.0.0.dist-info/METADATA
Imap2Dict_kiyoshirou-1.0.0.dist-info/WHEEL
Imap2Dict_kiyoshirou-1.0.0.dist-info/top_level.txt
Imap2Dict_kiyoshirou-1.0.0.dist-info/RECORD
