Metadata-Version: 2.1
Name: Imap2Dict_kiyoshirou
Version: 1.0.0
Summary: Automatically convert .doc and .docx and .xlsx and .pptx to .pdf format.
Author: Kiyoshirou Matsubara
Author-email: s2222035@stu.musashino-u.ac.jp
Maintainer: Kiyoshirou Matsubara
Maintainer-email: s2222035@stu.musashino-u.ac.jp
License: MIT
Keywords: docx,xlsx,pptx,pdf,convert,docx to pdf,xlsx to pdf,pptx to
Classifier: License :: OSI Approved :: MIT License
Classifier: Programming Language :: Python :: 3.6
Requires-Dist: os
Requires-Dist: comtypes
Requires-Dist: docx
Requires-Dist: xlsxwriter.workbook
Requires-Dist: pptx
Requires-Dist: subprocess
